leeeeon4_test_package/__init__.py
leeeeon4_test_package/cli.py
leeeeon4_test_package/leeeeon4_test_package.py
leeeeon4_test_package-0.0.5.dist-info/AUTHORS.rst
leeeeon4_test_package-0.0.5.dist-info/LICENSE
leeeeon4_test_package-0.0.5.dist-info/METADATA
leeeeon4_test_package-0.0.5.dist-info/WHEEL
leeeeon4_test_package-0.0.5.dist-info/entry_points.txt
leeeeon4_test_package-0.0.5.dist-info/top_level.txt
leeeeon4_test_package-0.0.5.dist-info/RECORD
