Metadata-Version: 2.1
Name: leeeeon4-test-package
Version: 0.0.5
Summary: A test package created to learn best practices regarding creating packages based on the course: Creating and Distributing Python Packages - https://twoscoopspress.thinkific.com/courses/creating-and-distributing-python-packages
Home-page: https://github.com/leeeeon4/leeeeon4_test_package
Author: Leon Michel Gorißen
Author-email: leon.gorissen@rwth-aachen.de
License: MIT license
Keywords: leeeeon4_test_package
Platform: UNKNOWN
Classifier: Development Status :: 2 - Pre-Alpha
Classifier: Intended Audience :: Developers
Classifier: License :: OSI Approved :: MIT License
Classifier: Natural Language :: English
Classifier: Programming Language :: Python :: 3
Classifier: Programming Language :: Python :: 3.6
Classifier: Programming Language :: Python :: 3.7
Classifier: Programming Language :: Python :: 3.8
Requires-Python: >=3.6
License-File: LICENSE
License-File: AUTHORS.rst
Requires-Dist: Click (>=7.0)
